auto_survey/__init__.py
auto_survey/ascii.py
auto_survey/cli.py
auto_survey/data_models.py
auto_survey/llm.py
auto_survey/pdf_conversion.py
auto_survey/search.py
auto_survey/summarisation.py
auto_survey/utils.py
auto_survey/writing.py
auto_survey-0.2.0.dist-info/METADATA
auto_survey-0.2.0.dist-info/WHEEL
auto_survey-0.2.0.dist-info/entry_points.txt
auto_survey-0.2.0.dist-info/licenses/LICENSE
auto_survey-0.2.0.dist-info/RECORD
