Metadata-Version: 2.4
Name: auto_survey
Version: 0.2.0
Summary: Automated literature surveys.
Project-URL: Repository, https://github.com/saattrupdan/auto-survey
Project-URL: Issues, https://github.com/saattrupdan/auto-survey/issues
Author-email: Dan Saattrup Smart <saattrupdan@gmail.com>
Maintainer-email: Dan Saattrup Smart <saattrupdan@gmail.com>
License: MIT License
License-File: LICENSE
Requires-Python: <4.0,>=3.11
Requires-Dist: click>=8.3.0
Requires-Dist: docling>=2.55.0
Requires-Dist: httpx==0.27.2
Requires-Dist: litellm>=1.77.7
Requires-Dist: python-dotenv>=1.1.1
Requires-Dist: termcolor>=3.1.0
